{
  "type": "playlist",
  "image": "playlist-images/sad.jpg",
  "playables": [
    {
      "type": "track",
      "trackId": 11679787
    },
    {
      "type": "track",
      "trackId": 29305484
    },
    {
      "type": "track",
      "trackId": 61666334
    },
    {
      "type": "track",
      "trackId": 36298617
    },
    {
      "type": "track",
      "trackId": 11811836
    },
    {
      "type": "track",
      "trackId": 29517198
    },
    {
      "type": "track",
      "trackId": 17907375
    },
    {
      "type": "track",
      "trackId": 60764084
    },
    {
      "type": "track",
      "trackId": 58855826
    },
    {
      "type": "track",
      "trackId": 61166974
    },
    {
      "type": "track",
      "trackId": 14359240
    },
    {
      "type": "track",
      "trackId": 22421976
    },
    {
      "type": "track",
      "trackId": 34062611
    },
    {
      "type": "track",
      "trackId": 118130
    },
    {
      "type": "track",
      "trackId": 53705765
    },
    {
      "type": "track",
      "trackId": 17338009
    },
    {
      "type": "track",
      "trackId": 50509011
    },
    {
      "type": "track",
      "trackId": 39198049
    },
    {
      "type": "track",
      "trackId": 59784373
    },
    {
      "type": "track",
      "trackId": 34340359
    },
    {
      "type": "track",
      "trackId": 60486836
    },
    {
      "type": "track",
      "trackId": 37073361
    },
    {
      "type": "track",
      "trackId": 29512870
    },
    {
      "type": "track",
      "trackId": 54964201
    },
    {
      "type": "track",
      "trackId": 8798499
    },
    {
      "type": "track",
      "trackId": 52483193
    },
    {
      "type": "track",
      "trackId": 61932336
    },
    {
      "type": "track",
      "trackId": 69199126
    },
    {
      "type": "track",
      "trackId": 67245607
    },
    {
      "type": "track",
      "trackId": 65303782
    },
    {
      "type": "track",
      "trackId": 68595002
    },
    {
      "type": "track",
      "trackId": 67433874
    },
    {
      "type": "track",
      "trackId": 67117125
    },
    {
      "type": "track",
      "trackId": 70656981
    },
    {
      "type": "track",
      "trackId": 42474702
    },
    {
      "type": "track",
      "trackId": 2974
    },
    {
      "type": "track",
      "trackId": 29531187
    },
    {
      "type": "track",
      "trackId": 55113027
    },
    {
      "type": "track",
      "trackId": 66017000
    },
    {
      "type": "track",
      "trackId": 41080230
    },
    {
      "type": "track",
      "trackId": 68005584
    },
    {
      "type": "track",
      "trackId": 70230992
    },
    {
      "type": "track",
      "trackId": 68005665
    },
    {
      "type": "track",
      "trackId": 62666532
    },
    {
      "type": "track",
      "trackId": 2202957
    },
    {
      "type": "track",
      "trackId": 63912321
    }
  ]
}
